oceansdb/__init__.py
oceansdb/cars.py
oceansdb/common.py
oceansdb/etopo.py
oceansdb/utils.py
oceansdb/version.py
oceansdb/woa.py
oceansdb/datasource/cars.json
oceansdb/datasource/etopo.json
oceansdb/datasource/woa.json
oceansdb/datasource/woa13.json
oceansdb/datasource/woa18.json
oceansdb-0.8.15.dist-info/AUTHORS.rst
oceansdb-0.8.15.dist-info/LICENSE.rst
oceansdb-0.8.15.dist-info/METADATA
oceansdb-0.8.15.dist-info/WHEEL
oceansdb-0.8.15.dist-info/top_level.txt
oceansdb-0.8.15.dist-info/RECORD
