Metadata-Version: 2.1
Name: oceansdb
Version: 0.8.15
Summary: Subsample ocean climatologies and reference data
Author: Guilherme Castelao
Author-email: guilherme@castelao.net
Project-URL: repository, https://github.com/castelao/oceansdb
Keywords: WOA,World Ocean Atlas,climatology,oceanography,ETOPO,temperature,salinity,bathymetry,CARS
Classifier: Development Status :: 4 - Beta
Classifier: Intended Audience :: Science/Research
Classifier: License :: OSI Approved :: BSD License
Classifier: Operating System :: OS Independent
Classifier: Programming Language :: Python :: 3
Classifier: Programming Language :: Python :: 3.7
Classifier: Programming Language :: Python :: 3.8
Classifier: Programming Language :: Python :: 3.9
Classifier: Programming Language :: Python :: 3.10
Classifier: Topic :: Scientific/Engineering
Requires-Python: >=3.7
License-File: LICENSE.rst
License-File: AUTHORS.rst
Requires-Dist: numpy (>=1.14)
Requires-Dist: scipy (>=1.1)
Requires-Dist: netCDF4 (>=1.2.4)
Requires-Dist: supportdata (>=0.1.3)
Provides-Extra: dev
Requires-Dist: twine (>=1.8.1) ; extra == 'dev'
Requires-Dist: sphinx (>=1.5.1) ; extra == 'dev'
Provides-Extra: test
Requires-Dist: hypothesis (>=6.29.3) ; extra == 'test'
Requires-Dist: pytest (>=5.0.0) ; extra == 'test'
Requires-Dist: pytest-cov[all] ; extra == 'test'
Requires-Dist: pip (>=9.0.1) ; extra == 'test'
Requires-Dist: flake8 (>=3.2.1) ; extra == 'test'
Requires-Dist: tox (>=2.3.3) ; extra == 'test'
Requires-Dist: coverage (>=4.2) ; extra == 'test'
Requires-Dist: supportdata (>=0.1.2) ; extra == 'test'
